distru_sdk/__init__.py
distru_sdk/async_client.py
distru_sdk/batch.py
distru_sdk/caching.py
distru_sdk/client.py
distru_sdk/exceptions.py
distru_sdk/logging.py
distru_sdk/retry.py
distru_sdk/webhooks.py
distru_sdk/resources/__init__.py
distru_sdk/resources/base.py
distru_sdk/resources/batches.py
distru_sdk/resources/companies.py
distru_sdk/resources/contacts.py
distru_sdk/resources/inventory.py
distru_sdk/resources/invoices.py
distru_sdk/resources/locations.py
distru_sdk/resources/orders.py
distru_sdk/resources/packages.py
distru_sdk/resources/products.py
distru_sdk/resources/purchases.py
distru_sdk-1.0.2.dist-info/METADATA
distru_sdk-1.0.2.dist-info/WHEEL
distru_sdk-1.0.2.dist-info/top_level.txt
distru_sdk-1.0.2.dist-info/RECORD
