Metadata-Version: 2.4
Name: distru-sdk
Version: 1.0.2
Summary: Official Python SDK for the Distru API - Cannabis supply chain management
Home-page: https://github.com/DistruApp/distru-api-sdk
Author: Distru Inc.
Author-email: "Distru Inc." <support@distru.com>
License: MIT
Project-URL: Homepage, https://distru.com
Project-URL: Documentation, https://github.com/DistruApp/distru-api-sdk/tree/main/python
Project-URL: Repository, https://github.com/DistruApp/distru-api-sdk
Project-URL: Issues, https://github.com/DistruApp/distru-api-sdk/issues
Keywords: distru,api,sdk,cannabis,supply-chain,inventory,compliance
Classifier: Development Status :: 5 - Production/Stable
Classifier: Intended Audience :: Developers
Classifier: License :: OSI Approved :: MIT License
Classifier: Operating System :: OS Independent
Classifier: Programming Language :: Python :: 3
Classifier: Programming Language :: Python :: 3.8
Classifier: Programming Language :: Python :: 3.9
Classifier: Programming Language :: Python :: 3.10
Classifier: Programming Language :: Python :: 3.11
Classifier: Programming Language :: Python :: 3.12
Classifier: Topic :: Software Development :: Libraries :: Python Modules
Classifier: Topic :: Internet :: WWW/HTTP
Requires-Python: >=3.8
Requires-Dist: httpx>=0.25.0
Requires-Dist: pydantic>=2.0.0
Requires-Dist: typing-extensions>=4.0.0; python_version < "3.11"
Provides-Extra: dev
Requires-Dist: pytest>=7.0.0; extra == "dev"
Requires-Dist: pytest-asyncio>=0.21.0; extra == "dev"
Requires-Dist: pytest-cov>=4.0.0; extra == "dev"
Requires-Dist: pytest-mock>=3.10.0; extra == "dev"
Requires-Dist: mypy>=1.0.0; extra == "dev"
Requires-Dist: black>=23.0.0; extra == "dev"
Requires-Dist: isort>=5.12.0; extra == "dev"
Requires-Dist: flake8>=6.0.0; extra == "dev"
Requires-Dist: responses>=0.23.0; extra == "dev"
Provides-Extra: docs
Requires-Dist: sphinx>=6.0.0; extra == "docs"
Requires-Dist: sphinx-rtd-theme>=1.2.0; extra == "docs"
Requires-Dist: sphinx-autodoc-typehints>=1.23.0; extra == "docs"
Dynamic: author
Dynamic: home-page
Dynamic: requires-python
